MANIFEST.in
README.txt
setup.cfg
setup.py
prism_rest_client/__init__.py
prism_rest_client/cache.py
prism_rest_client/client.py
prism_rest_client/collection.py
prism_rest_client/renderer.py
prism_rest_client/resource.py
prism_rest_client.egg-info/PKG-INFO
prism_rest_client.egg-info/SOURCES.txt
prism_rest_client.egg-info/dependency_links.txt
prism_rest_client.egg-info/not-zip-safe
prism_rest_client.egg-info/requires.txt
prism_rest_client.egg-info/top_level.txt
prism_rest_client/lib/__init__.py
prism_rest_client/lib/util.py