Metadata-Version: 1.1
Name: prism-rest-client
Version: 0.1
Summary: prism_rest_client
Home-page: https://github.com/elliotpeele/prism_rest_client
Author: Elliot Peele
Author-email: elliot@bentlogic.net
License: UNKNOWN
Keywords: web rest client
Platform: UNKNOWN
Classifier: Programming Language :: Python
Classifier: Topic :: Internet :: WWW/HTTP
